{
  "segmentId": 0,
  "audioResponse": {
    "audioUrl": "/audio/pride and prejudice_segment_0.mp3"
  },
  "sceneResponse": {
    "shots": [
      {
        "shotNumber": 1,
        "characters": [
          "Elizabeth Bennet",
          "Jane Bennet"
        ],
        "description": "Medium shot of Elizabeth and Jane sitting in a cozy drawing room, the warm firelight casting a soft glow on their faces. Elizabeth's expression is pensive as she holds a letter, while Jane watches her sister with concern.",
        "dialogue": null,
        "tone": "Contemplative, sisterly affection"
      },
      {
        "shotNumber": 2,
        "characters": [
          "Elizabeth Bennet"
        ],
        "description": "Close-up of Elizabeth's face, her brow furrowed as she reads the letter, the flickering flames reflecting in her eyes.",
        "dialogue": null,
        "tone": "Introspective, troubled"
      },
      {
        "shotNumber": 3,
        "characters": [
          "Jane Bennet",
          "Elizabeth Bennet"
        ],
        "description": "Over-the-shoulder shot of Jane, her face half-lit by the firelight, as she leans towards Elizabeth with a reassuring expression.",
        "dialogue": "\"What does the letter say, Lizzy?\"",
        "tone": "Gentle concern"
      },
      {
        "shotNumber": 4,
        "characters": [
          "Elizabeth Bennet",
          "Jane Bennet"
        ],
        "description": "Two-shot of the sisters, Elizabeth's face reflecting a mix of emotions as she looks up from the letter, meeting Jane's gaze.",
        "dialogue": "\"It is from Miss Bingley, informing me of their departure from Netherfield...\"",
        "tone": "Conflicted, melancholic"
      }
    ],
    "newCharacters": []
  }
}